{
  "BasicInfo": {
    "Name": "TypeScript",
    "Slug": "native_typescript",
    "Description": "Quickly start a simple TypeScript console project with node.",
    "Categories": [
      "Languages"
    ],
    "ProjectType": "native",
    "Languages": [
      "TypeScript"
    ]
  },
  "Runtime": {
    "RuntimeTemplate": "nodejs",
    "Envs": {
      "CLOUDIDE_CONFIG_LANGUAGE": "typescript",
      "CLOUDIDE_CONFIG_RUNTIME": "nodejs",
      "CLOUDIDE_DEFAULT_RUN_CONFIGURATION": "{\"name\":\"Run Application\",\"type\":\"node\",\"request\":\"launch\",\"runtimeExecutable\":\"npm\",\"runtimeArgs\":[\"run\",\"dev\"],\"cwd\":\"${workspaceFolder}\"}"
    },
    "Commands": {
      "BeforeStart": {
        "Name": ""
      },
      "AfterStart": {
        "Name": ""
      },
      "OnInit": {
        "Name": "init",
        "Script": [
          "bash",
          "-lc",
          "pnpm i"
        ]
      }
    }
  },
  "Ide": {},
  "Service": {}
}