{
    "BasicInfo": {
      "Name": "Moonbit",
      "Slug": "native_moonbit",
      "Description": "Quickly start a Moonbit 'Hello world' project in seconds.",
      "Version": "0.0.1",
      "Categories": [
        "Languages"
      ],
      "ProjectType": "native",
      "Languages": [
        "Moonbit"
      ]
    },
    "Runtime": {
      "RuntimeTemplate": "moonbit",
      "Envs": {
        "CLOUDIDE_CONFIG_LANGUAGE": "javascript",
        "CLOUDIDE_CONFIG_RUNTIME": "nodejs"
      },
      "Commands": {
        "BeforeStart": {
          "Name": ""
        },
        "AfterStart": {
          "Name": ""
        },
        "OnInit": {
          "Name": ""
        }
      }
    },
    "Ide": {},
    "Service": {}
  }
  